human_mouse/__init__.py
human_mouse/mouse.py
human_mouse/utils.py
human_mouse-0.1.2.dist-info/METADATA
human_mouse-0.1.2.dist-info/WHEEL
human_mouse-0.1.2.dist-info/top_level.txt
human_mouse-0.1.2.dist-info/RECORD
