Metadata-Version: 2.1
Name: human_mouse
Version: 0.1.2
Summary: A package that simulates realistic human-like mouse movements
Home-page: https://github.com/sarperavci/human_mouse
Author: Sarper AVCI
Author-email: sarperavci20@gmail.com
Project-URL: Bug Tracker, https://github.com/sarperavci/human_mouse/issues
Project-URL: Documentation, https://github.com/sarperavci/human_mouse#readme
Keywords: mouse,automation,human-like,movement,simulation,testing
Classifier: Development Status :: 4 - Beta
Classifier: Intended Audience :: Developers
Classifier: Programming Language :: Python :: 3
Classifier: Programming Language :: Python :: 3.10
Classifier: Programming Language :: Python :: 3.11
Classifier: License :: OSI Approved :: MIT License
Classifier: Operating System :: OS Independent
Classifier: Topic :: Software Development :: Libraries :: Python Modules
Classifier: Topic :: Software Development :: Testing
Requires-Python: >=3.10
Requires-Dist: numpy >=1.21.0
Requires-Dist: pyautogui >=0.9.53
Requires-Dist: scipy >=1.7.0
Provides-Extra: linux
Requires-Dist: python-xlib >=0.27 ; extra == 'linux'
